cdprox/__init__.py
cdprox/config.py
cdprox/main.py
cdprox/utils.py
cdproxy-1.4.dist-info/LICENSE
cdproxy-1.4.dist-info/METADATA
cdproxy-1.4.dist-info/WHEEL
cdproxy-1.4.dist-info/entry_points.txt
cdproxy-1.4.dist-info/top_level.txt
cdproxy-1.4.dist-info/RECORD
