Metadata-Version: 2.1
Name: cdproxy
Version: 1.4
Summary: A tool to manage Caddy reverse proxy configurations with Cloudflare DNS.
Home-page: https://github.com/yourusername/cdproxy
Author: Piotr Tamu (Thriveroute)
Author-email: your.email@example.com
Classifier: Programming Language :: Python :: 3
Classifier: License :: OSI Approved :: MIT License
Classifier: Operating System :: OS Independent
Requires-Python: >=3.11
License-File: LICENSE
Requires-Dist: requests
Requires-Dist: dnspython
Requires-Dist: boto3
Requires-Dist: python-dotenv
